ppi_net_builder/__init__.py
ppi_net_builder/src/__init__.py
ppi_net_builder/src/data.py
ppi_net_builder/src/fetch.py
ppi_net_builder/src/graph.py
ppi_net_builder-0.1.2.dist-info/licenses/LICENSE
ppi_net_builder-0.1.2.dist-info/METADATA
ppi_net_builder-0.1.2.dist-info/WHEEL
ppi_net_builder-0.1.2.dist-info/top_level.txt
ppi_net_builder-0.1.2.dist-info/RECORD
