Metadata-Version: 2.4
Name: ppi-net-builder
Version: 0.1.2
Summary: Protein-Protein Interaction (PPI) network construction and analysis using STRING-db (https://string-db.org/) in Python.
Author-email: Yu-Te Lin <qwerty239qwe@gmail.com>
License: MIT License
Project-URL: Homepage, https://github.com/qwerty239qwe/ppi_net_builder
Keywords: protein-protein interaction network,PPI,enrichment analysis,stringdb,string
Classifier: License :: OSI Approved :: MIT License
Classifier: Programming Language :: Python
Classifier: Programming Language :: Python :: 3
Requires-Python: >=3.9
License-File: LICENSE
Requires-Dist: pandas
Requires-Dist: requests
Requires-Dist: tqdm
Requires-Dist: igraph
Provides-Extra: dev
Requires-Dist: pytest>=7.0.0; extra == "dev"
Requires-Dist: pytest-cov>=4.0.0; extra == "dev"
Dynamic: license-file
